asynchronizer/__init__.py
asynchronizer-0.1.0a1.dist-info/DESCRIPTION.rst
asynchronizer-0.1.0a1.dist-info/METADATA
asynchronizer-0.1.0a1.dist-info/RECORD
asynchronizer-0.1.0a1.dist-info/WHEEL
asynchronizer-0.1.0a1.dist-info/metadata.json
asynchronizer-0.1.0a1.dist-info/top_level.txt
