Metadata-Version: 2.0
Name: asynchronizer
Version: 0.1.0a1
Summary: A simple module to make functions asynchronous
Home-page: https://github.com/Arsh23/asynchronizer
Author: arsh23
Author-email: programmer.arsh@gmail.com
License: MIT
Keywords: async asynchronous gevent
Platform: UNKNOWN
Classifier: Development Status :: 3 - Alpha
Classifier: Intended Audience :: Developers
Classifier: Topic :: Software Development
Classifier: License :: OSI Approved :: MIT License
Classifier: Programming Language :: Python :: 2
Classifier: Programming Language :: Python :: 2.6
Classifier: Programming Language :: Python :: 2.7
Classifier: Programming Language :: Python :: 3
Classifier: Programming Language :: Python :: 3.2
Classifier: Programming Language :: Python :: 3.3
Classifier: Programming Language :: Python :: 3.4
Requires-Dist: gevent
